<?xml version="1.0" ?><list><Unggah__Jadwal.Data__jadwal><Tanggal>2023-07-17</Tanggal><Waktu>1230</Waktu><Kegiatan>membersihkan sungai</Kegiatan><LokasiKegiatan>kaliurang</LokasiKegiatan><pembuat>rama</pembuat></Unggah__Jadwal.Data__jadwal><Unggah__Jadwal.Data__jadwal><Tanggal>2023-07-20</Tanggal><Waktu>1115</Waktu><Kegiatan>membershkan area embung uii</Kegiatan><LokasiKegiatan>embung belakang uii</LokasiKegiatan><pembuat>moza</pembuat></Unggah__Jadwal.Data__jadwal><Unggah__Jadwal.Data__jadwal><Tanggal>2023-07-23</Tanggal><Waktu>1530</Waktu><Kegiatan>membersihkan kali</Kegiatan><LokasiKegiatan>jalan kaliurang</LokasiKegiatan><pembuat>rahman</pembuat></Unggah__Jadwal.Data__jadwal><Unggah__Jadwal.Data__jadwal><Tanggal>2023-08-05</Tanggal><Waktu>830</Waktu><Kegiatan>jalan sehat sembari memungut sampah di jalan kaliurang</Kegiatan><LokasiKegiatan>jalan kaliurang</LokasiKegiatan><pembuat>Dini</pembuat></Unggah__Jadwal.Data__jadwal></list>